esub/__init__.py
esub/epipe.py
esub/esub.py
esub/submit.py
esub/utils.py
esub/scripts/__init__.py
esub/scripts/check_logs.py
esub/scripts/send_cmd.py
esub_epipe-1.12.1.dist-info/METADATA
esub_epipe-1.12.1.dist-info/WHEEL
esub_epipe-1.12.1.dist-info/entry_points.txt
esub_epipe-1.12.1.dist-info/licenses/AUTHORS.rst
esub_epipe-1.12.1.dist-info/licenses/LICENSE
esub_epipe-1.12.1.dist-info/RECORD
