Metadata-Version: 2.4
Name: esub-epipe
Version: 1.12.1
Project-URL: Source, https://cosmo-gitlab.phys.ethz.ch/cosmo_public/esub-epipe
Project-URL: Documentation, https://cosmo-docs.phys.ethz.ch/esub-epipe
Author-email: Dominik Zürcher <dominikz@phys.ethz.ch>, Silvan Fischbacher <silvanf@phys.ethz.ch>
License-Expression: MIT
License-File: AUTHORS.rst
License-File: LICENSE
Classifier: Programming Language :: Python
Classifier: Programming Language :: Python :: 3.9
Classifier: Programming Language :: Python :: 3.10
Classifier: Programming Language :: Python :: 3.11
Classifier: Programming Language :: Python :: 3.12
Requires-Python: >=3.9
Requires-Dist: argparse
Requires-Dist: coverage
Requires-Dist: ekit
Requires-Dist: numpy
Requires-Dist: portalocker
Requires-Dist: pylint
Requires-Dist: pyyaml
Requires-Dist: setuptools
Provides-Extra: dev
Requires-Dist: black; extra == 'dev'
Requires-Dist: flake8; extra == 'dev'
Requires-Dist: isort; extra == 'dev'
Requires-Dist: myst-parser; extra == 'dev'
Requires-Dist: pytest; extra == 'dev'
Requires-Dist: pytest-cov; extra == 'dev'
Requires-Dist: pytest-regtest; extra == 'dev'
Requires-Dist: ruff; extra == 'dev'
Requires-Dist: sphinx; extra == 'dev'
Requires-Dist: sphinx-pynpoint-theme; extra == 'dev'
Requires-Dist: tox; extra == 'dev'
Requires-Dist: twine; extra == 'dev'
Provides-Extra: docs
Requires-Dist: myst-parser; extra == 'docs'
Requires-Dist: nbsphinx; extra == 'docs'
Requires-Dist: recommonmark; extra == 'docs'
Requires-Dist: sphinx-copybutton; extra == 'docs'
Requires-Dist: sphinx-pynpoint-theme; extra == 'docs'
Requires-Dist: sphinx<7; extra == 'docs'
